docs/Makefile
docs/conf.py
docs/index.rst
docs/make.bat
docs/reference/analyse.rst
docs/reference/classes.rst
docs/reference/contour.rst
docs/reference/image.rst
docs/reference/index.rst
docs/reference/io.rst
docs/tutorial/index.rst
examples/README.rst
examples/contours/README.rst
examples/contours/boundary_a_star.py
examples/contours/boundary_chan_vese.py
examples/contours/boundary_contours.py
examples/contours/removing_small_bumps.py
examples/io/README.rst
examples/io/creating_rippleimage.py
examples/io/creating_rippleimageseries.py
examples/io/loading_a_directory.py
examples/io/loading_tiff.py
examples/visualisation/README.rst
examples/visualisation/plotting_a_timeseries.py
examples/visualisation/plotting_ripple_contour.py
examples/visualisation/plotting_ripple_image.py
examples/visualisation/plotting_ripple_image_series.py
examples/visualisation/ripple_animation.gif
licenses/LICENSE.rst
licenses/README.rst
licenses/TEMPLATE_LICENSE.rst
ripplemapper/__init__.py
ripplemapper/analyse.py
ripplemapper/classes.py
ripplemapper/contour.py
ripplemapper/image.py
ripplemapper/io.py
ripplemapper/version.py
ripplemapper/visualisation.py
ripplemapper/data/README.rst
ripplemapper/data/__init__.py
ripplemapper/data/example/1_00052_sample.rimg
ripplemapper/data/example/1_00052_sample.tif
ripplemapper/data/example/1_00205_sample.tif
ripplemapper/data/example/1_00375_sample.tif
ripplemapper/data/example/1_00443_sample.tif
ripplemapper/data/example/__init__.py
ripplemapper/data/example/example_contour.txt
ripplemapper/data/example/rimgs/1_00052_sample.rimg
ripplemapper/data/example/rimgs/1_00205_sample.rimg
ripplemapper/data/example/rimgs/1_00375_sample.rimg
ripplemapper/data/example/rimgs/1_00443_sample.rimg
ripplemapper/data/example/rimgs/image_series.rimgs
ripplemapper/tests/__init__.py
ripplemapper/tests/conftest.py
ripplemapper/tests/test_analyse.py
ripplemapper/tests/test_class_methods.py
ripplemapper/tests/test_classes.py
ripplemapper/tests/test_contour.py
ripplemapper-0.3.dist-info/METADATA
ripplemapper-0.3.dist-info/WHEEL
ripplemapper-0.3.dist-info/entry_points.txt
ripplemapper-0.3.dist-info/top_level.txt
ripplemapper-0.3.dist-info/RECORD
