Metadata-Version: 2.1
Name: ripplemapper
Version: 0.3
Summary: Tools for analysing the water air interface to programmatically detect surface waves.
Author-email: Alasdair Wilson <alasdair.wlsn@googlemail.com>
License: Copyright (c) 2024, Alasdair Wilson
Requires-Python: >=3.10
Requires-Dist: numpy >1.24.0
Requires-Dist: scipy >1.9.0
Requires-Dist: matplotlib >3.6
Requires-Dist: scikit-image >0.21
Requires-Dist: opencv-python >4.7.0
Provides-Extra: docs
Requires-Dist: sphinx >=5.0.0 ; extra == 'docs'
Requires-Dist: sphinx-changelog >=0.1 ; extra == 'docs'
Requires-Dist: sphinx-automodapi >=0.14.1 ; extra == 'docs'
Requires-Dist: sphinx-copybutton >=0.5.0 ; extra == 'docs'
Requires-Dist: sphinx-design >=0.2.0 ; extra == 'docs'
Requires-Dist: sphinx-gallery >=0.13.0 ; extra == 'docs'
Requires-Dist: sphinx-hoverxref >=1.3.0 ; extra == 'docs'
Requires-Dist: pydata-sphinx-theme >=0.15.4 ; extra == 'docs'
Requires-Dist: sphinxext-opengraph >=0.8 ; extra == 'docs'
Provides-Extra: tests
Requires-Dist: pytest-astropy >=0.11.0 ; extra == 'tests'
Requires-Dist: pytest-mpl >=0.16 ; extra == 'tests'
Requires-Dist: pytest-xdist >=3.0.2 ; extra == 'tests'
Requires-Dist: pytest >=7.1.0 ; extra == 'tests'
Requires-Dist: pytest-doctestplus >=1.1.0 ; extra == 'tests'
Requires-Dist: pytest-cov ; extra == 'tests'
